boardlib/__init__.py
boardlib/__main__.py
boardlib/api/__init__.py
boardlib/api/aurora.py
boardlib/api/moon.py
boardlib/db/__init__.py
boardlib/db/aurora.py
boardlib/util/__init__.py
boardlib/util/grades.py
boardlib-0.13.1.dist-info/METADATA
boardlib-0.13.1.dist-info/WHEEL
boardlib-0.13.1.dist-info/entry_points.txt
boardlib-0.13.1.dist-info/licenses/LICENSE
boardlib-0.13.1.dist-info/RECORD
