Metadata-Version: 2.4
Name: boardlib
Version: 0.13.1
Summary: Utilities for interacting with climbing board APIs
Project-URL: Homepage, https://github.com/lemeryfertitta/BoardLib
Project-URL: Issues, https://github.com/lemeryfertitta/BoardLib/issues
Author-email: Luke Emery-Fertitta <lemeryfertitta@gmail.com>
License-File: LICENSE
Classifier: License :: OSI Approved :: MIT License
Classifier: Operating System :: OS Independent
Classifier: Programming Language :: Python :: 3
Requires-Python: >=3.8
Requires-Dist: bs4
Requires-Dist: pandas
Requires-Dist: requests
